mathshelp/__init__.py
mathshelp-0.2.dist-info/LICENCE.txt
mathshelp-0.2.dist-info/METADATA
mathshelp-0.2.dist-info/WHEEL
mathshelp-0.2.dist-info/top_level.txt
mathshelp-0.2.dist-info/RECORD
