Metadata-Version: 2.1
Name: mathshelp
Version: 0.2
Summary: A simple python module for students
Author: Senath Sethmika
Author-email: senathsethmika@gmail.com
Classifier: Programming Language :: Python :: 3
Classifier: License :: OSI Approved :: MIT License
Classifier: Operating System :: OS Independent
License-File: LICENCE.txt
